{
  "filename": "into-the-red-7hab.zwo",
  "slug": "into-the-red-7hab",
  "downloadUrl": "https://mywhooshinfo.com/workouts/workout/into-the-red-7hab?do=exportZwo",
  "name": "Into the Red!",
  "description": "Now that you have gained some experience with interval training, you're ready to hit the high-intensity efforts. These Zone 6, or Anaerobic Capacity intervals are generally 30sec to 3min in duration. \n\n\n\nZone 6 intervals are generally completed in 'sets'. A set is a group of consecutive intervals. These are high intensity, hard intervals that require some concentration. \n\n\n\nYou have another ' set' when you have a long recovery before beginning more successive intervals.\n    \n\n\n    Similar workouts\n\n        \n            \n                \n                    \n                        Into the Red!\n                    \n                    \n                    \n                        44:00\n                        33TSS\n                        IF: 0.67\n                        chat\n\n                    \n                \n            \n        \n        \n            \n                \n                    \n                        Base Miles #3\n                    \n                    \n                    \n                        43:50\n                        34TSS\n                        IF: 0.68\n                        chat\n\n                    \n                \n            \n        \n        \n            \n                \n                    \n                        Stepped Intervals\n                    \n                    \n                    \n                        44:00\n                        43TSS\n                        IF: 0.77\n                        chat\n\n                    \n                \n            \n        \n        \n            \n                \n                    \n                        Base Miles #3\n                    \n                    \n                    \n                        43:50\n                        34TSS\n                        IF: 0.68\n                        chat\n\n                    \n                \n            \n        \n        \n            \n                \n                    \n                        Neuromuscular Power Surges #1\n                    \n                    \n                    \n                        44:00\n                        37TSS\n                        IF: 0.71\n\n\n                    \n                \n            \n        \n        \n            \n                \n                    \n                        Stepped Intervals\n                    \n                    \n                    \n                        44:00\n                        43TSS\n                        IF: 0.77\n                        chat\n\n                    \n                \n            \n        \n        \n            \n                \n                    \n                        Stepping up\n                    \n                    \n                    \n                        44:00\n                        43TSS\n                        IF: 0.77\n                        chat",
  "duration": "44:00",
  "tss": 33,
  "intensityFactor": 0.67,
  "steps": [
    {
      "type": "warmup",
      "duration": 300,
      "durationFormatted": "05:00",
      "powerLow": 40,
      "powerHigh": 75,
      "powerFormatted": "40% FTP - 75% FTP"
    },
    {
      "type": "steadystate",
      "duration": 60,
      "durationFormatted": "01:00",
      "powerLow": 50,
      "powerHigh": 50,
      "powerFormatted": "50%"
    },
    {
      "type": "steadystate",
      "duration": 120,
      "durationFormatted": "02:00",
      "powerLow": 90,
      "powerHigh": 90,
      "powerFormatted": "90%"
    },
    {
      "type": "steadystate",
      "duration": 180,
      "durationFormatted": "03:00",
      "powerLow": 50,
      "powerHigh": 50,
      "powerFormatted": "50%"
    },
    {
      "type": "steadystate",
      "duration": 30,
      "durationFormatted": "00:30",
      "powerLow": 121,
      "powerHigh": 121,
      "powerFormatted": "121%"
    },
    {
      "type": "steadystate",
      "duration": 180,
      "durationFormatted": "03:00",
      "powerLow": 50,
      "powerHigh": 50,
      "powerFormatted": "50%"
    },
    {
      "type": "steadystate",
      "duration": 300,
      "durationFormatted": "05:00",
      "powerLow": 65,
      "powerHigh": 65,
      "powerFormatted": "65%"
    },
    {
      "type": "steadystate",
      "duration": 30,
      "durationFormatted": "00:30",
      "powerLow": 121,
      "powerHigh": 121,
      "powerFormatted": "121%"
    },
    {
      "type": "steadystate",
      "duration": 180,
      "durationFormatted": "03:00",
      "powerLow": 50,
      "powerHigh": 50,
      "powerFormatted": "50%"
    },
    {
      "type": "cooldown",
      "duration": 420,
      "durationFormatted": "07:00",
      "powerLow": 55,
      "powerHigh": 45,
      "powerFormatted": "55% FTP - 45% FTP"
    }
  ],
  "isValid": true
}